LICENSE
MANIFEST.in
README.md
README.txt
setup.py
django_fabv/__init__.py
django_fabv/admin.py
django_fabv/helpers.py
django_fabv/middleware.py
django_fabv/models.py
django_fabv/statistics.py
django_fabv.egg-info/PKG-INFO
django_fabv.egg-info/SOURCES.txt
django_fabv.egg-info/dependency_links.txt
django_fabv.egg-info/top_level.txt
django_fabv/fixtures/slogan.json
django_fabv/management/__init__.py
django_fabv/management/commands/__init__.py
django_fabv/management/commands/fabv.py
django_fabv/migrations/0001_initial.py
django_fabv/migrations/0002_initial.py
django_fabv/migrations/__init__.py
django_fabv/templatetags/__init__.py
django_fabv/templatetags/fabv_tags.py
django_fabv/tests/__init__.py
django_fabv/tests/tests.py
django_fabv/tests/urls.py
django_fabv/tests/templates/404.html
django_fabv/tests/templates/index.html
django_fabv/tests/templates/landing.html
django_fabv/tests/templates/persistence.html
django_fabv/tests/templates/signup.html
django_fabv/tests/templates/test.html