Metadata-Version: 1.0
Name: django-fabv
Version: 0.1.1
Summary: A/B module for Django based on ABingo
Home-page: https://pypi.python.org/pypi/django_fabv/0.1.0
Author: Bob Jansen
Author-email: bob.jansen@veneficus.nl
License: 3-clause BSD
Platform: UNKNOWN
